{
	"displayName": "SalesforceDocs Markdown Preview",
	"description": "Provides preview for Markdown Using Remark Processor.",
	"salesforcedocs.preview.breaks.desc": "Sets how line-breaks are rendered in the markdown preview. Setting it to 'true' creates a <br> for newlines inside paragraphs.",
	"salesforcedocs.preview.doubleClickToSwitchToEditor.desc": "Double click in the markdown preview to switch to the editor.",
	"salesforcedocs.preview.markEditorSelection.desc": "Mark the current editor selection in the markdown preview.",
	"salesforcedocs.preview.scrollEditorWithPreview.desc": "When a markdown preview is scrolled, update the view of the editor.",
	"salesforcedocs.preview.scrollPreviewWithEditor.desc": "When a markdown editor is scrolled, update the view of the preview.",
	"salesforcedocs.preview.title": "Open SalesforceDocs Preview",
	"salesforcedocs.previewSide.title": "Open SalesforceDocs Preview to the Side",
	"salesforcedocs.showLockedPreviewToSide.title": "Open Locked SalesforceDocs Preview to the Side",
	"salesforcedocs.showSource.title": "Show Markdown",
	"salesforcedocs.styles.dec": "A list of URLs or local paths to CSS style sheets to use from the markdown preview. Relative paths are interpreted relative to the folder open in the explorer. If there is no open folder, they are interpreted relative to the location of the markdown file. All '\\' need to be written as '\\\\'.",
	"salesforcedocs.showPreviewSecuritySelector.title": "Change Preview Security Settings",
	"salesforcedocs.trace.desc": "Enable debug logging for the markdown extension.",
	"salesforcedocs.preview.refresh.title": "Refresh Preview",
	"salesforcedocs.preview.toggleLock.title": "Toggle Preview Locking",
	"configuration.salesforcedocs.preview.openMarkdownLinks.description": "Controls how links to other markdown files in the markdown preview should be opened.",
	"configuration.salesforcedocs.preview.openMarkdownLinks.inEditor": "Try to open links in the editor",
	"configuration.salesforcedocs.preview.openMarkdownLinks.inPreview": "Try to open links in the markdown preview",
	"configuration.salesforcedocs.links.openLocation.description": "Controls where links in markdown files should be opened.",
	"configuration.salesforcedocs.links.openLocation.currentGroup": "Open links in the active editor group.",
	"configuration.salesforcedocs.links.openLocation.beside": "Open links beside the active editor.",
	"configuration.salesforcedocs.preview.style.preset.description": "Choose the base style preset for your Preview",
	"configuration.salesforcedocs.preview.style.preset.salesforcedocs": "Choose Salesforcedocs styling for your preview",
	"configuration.salesforcedocs.preview.style.preset.VSCode": "Choose basic VS Code markdown styling for your preview"
}